pycabanas/__init__.py
pycabanas/analysis.py
pycabanas/global_routines.py
pycabanas-0.0.11.dist-info/LICENSE
pycabanas-0.0.11.dist-info/METADATA
pycabanas-0.0.11.dist-info/WHEEL
pycabanas-0.0.11.dist-info/top_level.txt
pycabanas-0.0.11.dist-info/RECORD
