Metadata-Version: 2.1
Name: pycabanas
Version: 0.0.11
Summary: Spin Glass Analysis
Home-page: https://github.com/ocabanas/pycabanas
Author: Oriol Cabanas
Author-email: oriol.cabanas@gmail.com
License: MIT
Platform: UNKNOWN
Classifier: Development Status :: 4 - Beta
Classifier: Intended Audience :: Developers
Classifier: Topic :: Internet
Classifier: License :: OSI Approved :: MIT License
Classifier: Programming Language :: Python
Classifier: Programming Language :: Python :: 3
Classifier: Programming Language :: Python :: 3.6
License-File: LICENSE
Requires-Dist: numpy
Requires-Dist: numba
Requires-Dist: matplotlib
Requires-Dist: scipy
